db_rpc_client_py/__init__.py
db_rpc_client_py-0.1.0.dist-info/METADATA
db_rpc_client_py-0.1.0.dist-info/WHEEL
db_rpc_client_py-0.1.0.dist-info/RECORD
